cm/__init__.py
cm/functions.py
cm/launcher.py
cm/main_operator.py
cm/modules.py
cm/terminal.py
cm/wlistener.py
cm/configs/__init__.py
cm/configs/config.py
cm/configs/settings.py
cm/gcore_interaction/__init__.py
cm/gcore_interaction/db_functions.py
cm/gcore_interaction/db_functions_higher.py
cm/gcore_interaction/tests/__init__.py
cm/gcore_interaction/tests/test_db_function.py
cm/imgs/__init__.py
cm/imgs/abort.png
cm/imgs/abortFiltres.png
cm/imgs/abortFiltresZ.png
cm/imgs/abortRound.png
cm/imgs/abortRoundUnactive.png
cm/imgs/abortRoundZ.png
cm/imgs/abortZ.png
cm/imgs/accept.png
cm/imgs/acceptZ.png
cm/imgs/addComm.png
cm/imgs/auto_gate_control.png
cm/imgs/auto_gate_controlZ.png
cm/imgs/backscreen — копия.png
cm/imgs/backscreen.png
cm/imgs/backscreen2.png
cm/imgs/calendarwin.png
cm/imgs/cancel.png
cm/imgs/cancelZ.png
cm/imgs/cancel_tare.png
cm/imgs/car_in.png
cm/imgs/car_out.png
cm/imgs/change.png
cm/imgs/changeZ.png
cm/imgs/chatDecline.png
cm/imgs/chatbg.png
cm/imgs/chatcommit.png
cm/imgs/chatexit.png
cm/imgs/chaticon.png
cm/imgs/choosePol.png
cm/imgs/close.png
cm/imgs/closeZ.png
cm/imgs/close_recs.png
cm/imgs/currentEvents.png
cm/imgs/decline.png
cm/imgs/declineZ.png
cm/imgs/disputswin.png
cm/imgs/ensureCloseRec.png
cm/imgs/enter.png
cm/imgs/enterZ.png
cm/imgs/exit.png
cm/imgs/exitZ.png
cm/imgs/exitwin.png
cm/imgs/export_excel.png
cm/imgs/export_excelZ.png
cm/imgs/fakeTree.png
cm/imgs/forbwin.png
cm/imgs/frontscreen.png
cm/imgs/gateL.png
cm/imgs/gateR.png
cm/imgs/gate_arrow.png
cm/imgs/gate_base.png
cm/imgs/latecarswin.png
cm/imgs/lateconfirmwin.png
cm/imgs/loadingWin.png
cm/imgs/lock.png
cm/imgs/lockZ.png
cm/imgs/lock_screen.png
cm/imgs/login.png
cm/imgs/logo.png
cm/imgs/mainL.png
cm/imgs/mainLT.png
cm/imgs/mainLZ.png
cm/imgs/manual_control_info_bar.png
cm/imgs/manual_gate_control.png
cm/imgs/manual_gate_controlZ.png
cm/imgs/minimize.png
cm/imgs/minimizeZ.png
cm/imgs/newCar.png
cm/imgs/no.png
cm/imgs/noZ.png
cm/imgs/ok.png
cm/imgs/okZ.png
cm/imgs/open.png
gravity_front-1.4.0.dist-info/LICENSE
gravity_front-1.4.0.dist-info/METADATA
gravity_front-1.4.0.dist-info/WHEEL
gravity_front-1.4.0.dist-info/top_level.txt
gravity_front-1.4.0.dist-info/RECORD
