Metadata-Version: 2.1
Name: gravity-front
Version: 1.4.0
Author: PunchyArchy
License-File: LICENSE
Requires-Dist: pillow
Requires-Dist: pyscreenshot
Requires-Dist: tkcalendar
Requires-Dist: screeninfo
Requires-Dist: gtki-module-treeview (==2.1)
Requires-Dist: gtki-module-orup-errors (==1.31)
Requires-Dist: qsct
Requires-Dist: ar-one-qdk (==0.1.6)
Requires-Dist: cmadb (==0.0.1)
Requires-Dist: cm-qdk (==0.0.1)
Requires-Dist: qodex-pi
Requires-Dist: gtki-module-exex
